{
  "appPageId" : "1c2dcdf9-101c-4807-9ee1-ecf3bffb4f77",
  "componentName" : "siteforce:sldsTwoCol84Layout",
  "dataProviders" : [ ],
  "id" : "08b29d0d-d294-4d25-89af-52a8e96b31f7",
  "label" : "Article Detail",
  "regions" : [ {
    "id" : "2bdfd58b-31e7-42a1-8c15-b8d52debff07",
    "regionName" : "header",
    "type" : "region"
  }, {
    "components" : [ {
      "componentAttributes" : {
        "uniqueNameOrId" : "{!urlName}"
      },
      "componentName" : "forceCommunity:breadcrumbs",
      "id" : "250b5dc7-600a-4c1c-b5f5-c69b680cc0f8",
      "renderPriority" : "NEUTRAL",
      "renditionMap" : { },
      "type" : "component"
    }, {
      "componentAttributes" : {
        "enableVoting" : true,
        "recordId" : "{!recordId}",
        "showTitleInArticleHeader" : true,
        "showTopicPills" : true,
        "urlName" : "{!urlName}"
      },
      "componentName" : "selfService:singleArticleView",
      "id" : "0963c0d9-9562-44e4-9cb3-fbf01175f288",
      "renderPriority" : "NEUTRAL",
      "renditionMap" : { },
      "type" : "component"
    }, {
      "componentAttributes" : {
        "context" : "RECORD",
        "recordId" : "{!recordId}",
        "width" : "WIDE"
      },
      "componentName" : "forceCommunity:feedPublisher",
      "id" : "1102ee11-dce1-4d70-9350-c9f4930532c3",
      "renderPriority" : "NEUTRAL",
      "renditionMap" : { },
      "type" : "component"
    }, {
      "componentAttributes" : {
        "canChangeSorting" : false,
        "defaultFilter" : "",
        "defaultSortOrderHomeFeed" : "Relevance",
        "defaultSortOrderTopicsFeed" : "Relevance",
        "feedDesign" : "DEFAULT",
        "hasFeedSearch" : false,
        "subjectId" : "{!recordId}",
        "type" : "Record"
      },
      "componentName" : "forceCommunity:forceCommunityFeed",
      "id" : "60bd7793-752b-4e46-9e7f-480dc4c06ef6",
      "renderPriority" : "NEUTRAL",
      "renditionMap" : { },
      "type" : "component"
    } ],
    "id" : "13f44b11-7a80-4a35-b9c3-3faf7bf92b5b",
    "regionName" : "content",
    "type" : "region"
  }, {
    "components" : [ {
      "componentAttributes" : {
        "buttonAlignment" : "center",
        "buttonBgColor" : "",
        "buttonBgHoverColor" : "",
        "buttonBorderColor" : "",
        "buttonMaxWidth" : 100,
        "buttonRadius" : 0,
        "buttonTextColor" : "",
        "buttonTextHoverColor" : "",
        "recordId" : "{!recordId}",
        "showNotificationMenu" : false
      },
      "componentName" : "forceCommunity:follow",
      "id" : "9df14d91-33d6-41c8-8db1-e2da8fcf6e1e",
      "renderPriority" : "NEUTRAL",
      "renditionMap" : { },
      "type" : "component"
    }, {
      "componentAttributes" : {
        "numberOfItems" : 5,
        "showViewCounts" : true,
        "title" : "Related Articles"
      },
      "componentName" : "selfService:similarArticles42",
      "id" : "06d4d6af-93a2-43e7-841b-dbbc0c7e3ef5",
      "renderPriority" : "NEUTRAL",
      "renditionMap" : { },
      "type" : "component"
    }, {
      "componentAttributes" : {
        "numberOfArticles" : 5,
        "title" : "Trending Articles",
        "topicId" : "{!topicId}"
      },
      "componentName" : "selfService:topicTrendingArticles42",
      "id" : "983c1f70-a93e-451c-878a-aad8e83ec1ae",
      "renderPriority" : "NEUTRAL",
      "renditionMap" : { },
      "type" : "component"
    } ],
    "id" : "c2d6ffa8-f606-4ec3-b198-adc30967bd44",
    "regionName" : "sidebar",
    "type" : "region"
  }, {
    "id" : "66eda5a4-87a3-41c4-b0fd-9564bcffa7af",
    "regionName" : "footer",
    "type" : "region"
  }, {
    "components" : [ {
      "componentAttributes" : {
        "customHeadTags" : "",
        "description" : "{!Record.Summary}",
        "title" : "{!Record._Title}"
      },
      "componentName" : "forceCommunity:seoAssistant",
      "id" : "a006b2b1-bd44-49a1-a244-801a39a0157a",
      "renditionMap" : { },
      "type" : "component"
    } ],
    "id" : "9e12aeb5-4fc1-4f55-8f33-7033c3239259",
    "regionName" : "sfdcHiddenRegion",
    "type" : "region"
  } ],
  "themeLayoutType" : "Inner",
  "type" : "view",
  "viewType" : "article"
}